<?xml version="1.0" encoding="UTF-8"?>


<info>

<info1>
<sl_no>23</sl_no>
<name>John Carter</name>
<admissionDate>

<day>25</day>
<month>12</month>
<year>2015</year>

</admissionDate>

</info1>


<info2>

<sl_no>29</sl_no>
<name>Bob Marshal</name>
<admissionDate>

<day>23</day>
<month>01</month>
<year>1999</year>

</admissionDate>

</info2>



<info3>

<sl_no>35</sl_no>
<name>Clark Kent</name>
<admissionDate>

<day>17</day>
<month>06</month>
<year>2005</year>

</admissionDate>

</info3>

</info>





